jtd/__init__.py
jtd/schema.py
jtd/validate.py
jtd/tests/__init__.py
jtd/tests/test_schema.py
jtd/tests/test_validate.py
jtd-0.0.1.dist-info/LICENSE
jtd-0.0.1.dist-info/METADATA
jtd-0.0.1.dist-info/WHEEL
jtd-0.0.1.dist-info/top_level.txt
jtd-0.0.1.dist-info/RECORD
