Metadata-Version: 2.1
Name: jtd
Version: 0.0.1
Summary: A Python implementation of JSON Type Definition
Home-page: https://github.com/jsontypedef/json-typedef-py
Author: JSON Typedef Contributors
Author-email: friends@jsontypedef.com
License: UNKNOWN
Platform: UNKNOWN
Classifier: Programming Language :: Python :: 3
Classifier: License :: OSI Approved :: MIT License
Classifier: Operating System :: OS Independent
Requires-Python: >=3.6
Requires-Dist: strict-rfc3339 (>=0.7)
